Metadata-Version: 1.0
Name: gauss-bin-ian-distributions
Version: 1.1
Summary: Gaussian and Binomial distributions
Home-page: UNKNOWN
Author: Anirudhan K
Author-email: UNKNOWN
License: UNKNOWN
Platform: UNKNOWN
